sslap/__init__.py
sslap/_auction.cp38-win_amd64.pyd
sslap/auction.cp38-win_amd64.pyd
sslap/auction_.cp38-win_amd64.pyd
sslap/auction_solve.py
sslap/auctionx.cp38-win_amd64.pyd
sslap/check_feasible.py
sslap/feasibility.cp38-win_amd64.pyd
sslap/feasibility_.cp38-win_amd64.pyd
sslap/tester.py
sslap-0.2.5.dist-info/LICENSE.txt
sslap-0.2.5.dist-info/METADATA
sslap-0.2.5.dist-info/WHEEL
sslap-0.2.5.dist-info/top_level.txt
sslap-0.2.5.dist-info/RECORD
