Metadata-Version: 2.1
Name: sslap
Version: 0.2.5
Summary: Super Sparse Linear Assignment Problems Solver
Home-page: http://github.com/OllieBoyne/sslap
Author: Ollie Boyne
Author-email: ollieboyne@gmail.com
License: MIT
Keywords: super sparse linear assignment problem solve lap auction algorithm
Platform: UNKNOWN
Requires-Dist: numpy
Requires-Dist: matplotlib
Requires-Dist: tqdm
Requires-Dist: scipy
Requires-Dist: cython
